biotmed_dispatcher_sdk/__init__.py
biotmed_dispatcher_sdk/api_client.py
biotmed_dispatcher_sdk/api_response.py
biotmed_dispatcher_sdk/configuration.py
biotmed_dispatcher_sdk/exceptions.py
biotmed_dispatcher_sdk/py.typed
biotmed_dispatcher_sdk/rest.py
biotmed_dispatcher_sdk/api/__init__.py
biotmed_dispatcher_sdk/api/health_check_api_api.py
biotmed_dispatcher_sdk/api/interception_api_api.py
biotmed_dispatcher_sdk/api/subscription_api_api.py
biotmed_dispatcher_sdk/models/__init__.py
biotmed_dispatcher_sdk/models/create_interception_request.py
biotmed_dispatcher_sdk/models/delete_interception_request.py
biotmed_dispatcher_sdk/models/error_response.py
biotmed_dispatcher_sdk/models/filter_v2.py
biotmed_dispatcher_sdk/models/interception_response.py
biotmed_dispatcher_sdk/models/metadata.py
biotmed_dispatcher_sdk/models/order.py
biotmed_dispatcher_sdk/models/page_metadata.py
biotmed_dispatcher_sdk/models/search_request_v2.py
biotmed_dispatcher_sdk/models/search_response_interception_response.py
biotmed_dispatcher_sdk/models/search_response_subscribe_response.py
biotmed_dispatcher_sdk/models/subscribe_request.py
biotmed_dispatcher_sdk/models/subscribe_response.py
biotmed_dispatcher_sdk/models/unsubscribe_request.py
biotmed_dispatcher_sdk/models/version_response.py
biotmed_dispatcher_sdk-2.3.40.dist-info/METADATA
biotmed_dispatcher_sdk-2.3.40.dist-info/WHEEL
biotmed_dispatcher_sdk-2.3.40.dist-info/top_level.txt
biotmed_dispatcher_sdk-2.3.40.dist-info/RECORD
